{"vocabulary": [["immigrer", "to immigrate"],
["un immigré", "an immigrant"],
["émigrer aux USA", "to migrate to the USA"],
["être attiré par un pays", "to be attracted by a country"],
["un candidat à l'immigration", "a would-be immigrant"],
["pousser qqun à émigrer", "to push sb to emigrate"],
["fuir un pays", "to flee a country"],
["échapper à la pauvreté", "to escape poverty"],
["chercher à fuir la guerre", "to seek refuge from the war"],
["chercher l'asile politique", "to seek political asylum"],
["chercher une vie meilleure", "to be in search of a better life"],
["l'attrait d'emplois bien rémunérés", "the lure of well-paid jobs"],
["chercher des salaires plus élevés", "to look for higher wages"],
["faire fortune", "to make a fortune"],
["rompre avec le passé", "to break with the past"],
["partir de rien", "to start from scratch"],
["prendre un nouveau départ", "to start anew"],
["être confronté à des difficultés", "to be faced with difficulties"],
["être exploité", "to be exploited"],
["un atelier clandestin", "a sweatshop"],
["surmonter les obstacles", "to overcome obstacles"],
["la barrière de la langue", "the language barrier"],
["s'intégrer", "to integrate"],
["une politique d'immigration", "an immigration policy"],
["fermer ses frontières", "to seal one's borders"],
["endiguer le flot des immigrés", "to stem the flow of immigrants"],
["imposer des quotas", "to impose quotas"],
["être refoulé à la frontière", "to be turned away at the border"],
["renforcer les contrôles aux frontières", "to tighten border controls"],
["être expulsé d'un pays", "to be expelled from a country"],
["l'immigration clandestine", "illegal immigration"],
["un immigré clandestin", "an illegal"],
["un étranger clandestin", "an illegal alien"],
["un passager clandestin", "a stowaway"],
["un travailleur immigré", "a guest worker"],
["les sans-papiers", "the undocumented"],
["un passeur", "a smuggler"],
["un faux passeport", "a fake passport"],
["une moyenne de", "an average of"],
["la déshydratation", "dehydration"],
["ne pas correspondre à ses attentes", "to fall short of one's expectations"],
["entrer clandestinement en Grande-Bretagne", "to sneak into Britain"],
["contribuer à compenser", "to help offset"],
["le vieillissement de la population", "ageing population"],
["les années à venir", "the coming years"],
["un sujet très controversé", "a higly controversial issue"]],
"description":{
        "author":"Raph",
        "date":"2012-12-03",
        "number of use":0
    },
    "header":
    ["french", "english"]
}